climetlab_maelstrom_power_production/__init__.py
climetlab_maelstrom_power_production/config.py
climetlab_maelstrom_power_production/constants/__init__.py
climetlab_maelstrom_power_production/constants/a_b.py
climetlab_maelstrom_power_production/dataset.py
climetlab_maelstrom_power_production/merger.py
climetlab_maelstrom_power_production/production/__init__.py
climetlab_maelstrom_power_production/production/production.py
climetlab_maelstrom_power_production/weather/__init__.py
climetlab_maelstrom_power_production/weather/abc.py
climetlab_maelstrom_power_production/weather/merger.py
climetlab_maelstrom_power_production/weather/model_level.py
climetlab_maelstrom_power_production/weather/pressure_level.py
climetlab_maelstrom_power_production/weather/surface_level.py
climetlab_maelstrom_power_production-0.2.2.dist-info/LICENSE
climetlab_maelstrom_power_production-0.2.2.dist-info/METADATA
climetlab_maelstrom_power_production-0.2.2.dist-info/WHEEL
climetlab_maelstrom_power_production-0.2.2.dist-info/entry_points.txt
climetlab_maelstrom_power_production-0.2.2.dist-info/RECORD
