Metadata-Version: 2.1
Name: climetlab-maelstrom-power-production
Version: 0.2.2
Summary: CliMetLab plugin for the dataset climetlab-plugin-a6/maelstrom-production-forecasts.
Home-page: https://climetlab.readthedocs.io/en/latest/
License: Apache-2.0
Keywords: meteorology,weather,climate,wind power
Author: Fabian Emmerich
Author-email: fabian.emmerich@4-cast.de
Requires-Python: >=3.9,<4.0
Classifier: Development Status :: 3 - Alpha
Classifier: Intended Audience :: Developers
Classifier: License :: OSI Approved :: Apache Software License
Classifier: Operating System :: OS Independent
Classifier: Programming Language :: Python :: 3
Classifier: Programming Language :: Python :: 3.9
Classifier: Programming Language :: Python :: 3.10
Classifier: Programming Language :: Python :: 3.11
Classifier: Programming Language :: Python :: 3.7
Classifier: Programming Language :: Python :: 3.8
Classifier: Programming Language :: Python :: Implementation :: CPython
Classifier: Programming Language :: Python :: Implementation :: PyPy
Requires-Dist: climetlab (>=0.11.9,<0.12.0)
Requires-Dist: numpy (>=1.26.0,<2.0.0)
Project-URL: Repository, https://github.com/4castRenewables/climetlab-plugin-a6
